pandaspublisher/__init__.py
pandaspublisher/generate.py
pandaspublisher-0.1.1.dist-info/LICENSE
pandaspublisher-0.1.1.dist-info/METADATA
pandaspublisher-0.1.1.dist-info/WHEEL
pandaspublisher-0.1.1.dist-info/top_level.txt
pandaspublisher-0.1.1.dist-info/RECORD
