Metadata-Version: 2.1
Name: pandaspublisher
Version: 0.1.1
Summary: A Python package for generating customizable HTML and PDF reports from Pandas DataFrames and Jinja2 templates
Author-email: Jason Flittner <jason.flittner@gmail.com>
License: Apache License
Project-URL: Homepage, https://github.com/jflittner/PandasPublisher
Project-URL: Bug Tracker, https://github.com/jflittner/PandasPublisher/issues
Requires-Python: >=3.7
License-File: LICENSE
Requires-Dist: pandas
Requires-Dist: jinja2
Requires-Dist: weasyprint
